{
  "id": 1190,
  "date": "2026-07-04",
  "lunar_month": "చైత్ర",
  "paksha": "బహుళ",
  "thithi": "పంచమి",
  "thithi_end": "14:04:00",
  "nakshatram": "జ్యేష్ట",
  "nakshatram_end": "03:35:00",
  "varjyam_time": "7:10 AM - 8:57 AM",
  "durmuhurtham_1": "8:21 AM - 9:10 AM",
  "durmuhurtham_2": "10:51 PM - 11:38 PM",
  "sunrise": "05:47 AM",
  "sunset": "06:39 PM",
  "moonrise": "09:55 PM",
  "moonset": "09:11 AM",
  "abhijit_muhurtham": "11:49 AM - 12:37 PM",
  "amrita_kalam": "10:24 PM - 11:49 PM",
  "brahma_muhurtham": "04:11 AM - 04:59 AM",
  "pratah_sandhya": "05:32 AM - 06:47 AM",
  "vijaya_muhurtham": "04:15 PM - 05:03 PM",
  "godhuli_muhurtham": "06:24 PM - 06:54 PM",
  "sayam_sandhya": "06:39 PM - 07:54 PM",
  "nishita_muhurtham": "11:49 PM - 12:37 AM",
  "festivals": []
}