{
  "id": 1399,
  "date": "2026-02-11",
  "lunar_month": "ఆశ్వయుజ",
  "paksha": "బహుళ",
  "thithi": "అష్టమి",
  "thithi_end": "16:52:00",
  "nakshatram": "పుష్యమి",
  "nakshatram_end": "09:00:00",
  "varjyam_time": "9:05 AM - 10:35 AM",
  "durmuhurtham_1": "12:06 PM - 12:52 PM",
  "durmuhurtham_2": "2:23 PM - 3:09 PM",
  "sunrise": "06:33 AM",
  "sunset": "06:13 PM",
  "moonrise": "01:26 AM",
  "moonset": "12:53 PM",
  "abhijit_muhurtham": "11:59 AM - 12:47 PM",
  "amrita_kalam": "09:58 PM - 11:23 PM",
  "brahma_muhurtham": "04:57 AM - 05:45 AM",
  "pratah_sandhya": "06:18 AM - 07:33 AM",
  "vijaya_muhurtham": "03:49 PM - 04:37 PM",
  "godhuli_muhurtham": "05:58 PM - 06:28 PM",
  "sayam_sandhya": "06:13 PM - 07:28 PM",
  "nishita_muhurtham": "11:59 PM - 12:47 AM",
  "festivals": []
}