{
  "id": 1148,
  "date": "2026-02-24",
  "lunar_month": "ఫాల్గుణ",
  "paksha": "శుద్ధ",
  "thithi": "సప్తమి / అష్టమి",
  "thithi_end": "7:48 AM / 5:17 AM",
  "nakshatram": "కృత్తిక",
  "nakshatram_end": "15:56:00",
  "varjyam_time": "లేదు",
  "durmuhurtham_1": "8:51 AM - 9:36 AM",
  "durmuhurtham_2": "10:57 PM - 11:48 PM",
  "sunrise": "06:27 AM",
  "sunset": "06:16 PM",
  "moonrise": "11:23 AM",
  "moonset": "N/A",
  "abhijit_muhurtham": "11:58 AM - 12:46 PM",
  "amrita_kalam": "10:01 PM - 11:26 PM",
  "brahma_muhurtham": "04:51 AM - 05:39 AM",
  "pratah_sandhya": "06:12 AM - 07:27 AM",
  "vijaya_muhurtham": "03:52 PM - 04:40 PM",
  "godhuli_muhurtham": "06:01 PM - 06:31 PM",
  "sayam_sandhya": "06:16 PM - 07:31 PM",
  "nishita_muhurtham": "11:57 PM - 12:45 AM",
  "festivals": []
}